budapest-go-api/__init__.py
budapest-go-api/budapestgoapi.py
budapest_go_api/__init__.py
budapest_go_api/budapestgoapi.py
bkkapi-0.0.3.dist-info/LICENSE
bkkapi-0.0.3.dist-info/METADATA
bkkapi-0.0.3.dist-info/WHEEL
bkkapi-0.0.3.dist-info/top_level.txt
bkkapi-0.0.3.dist-info/RECORD
