Metadata-Version: 2.1
Name: bkkapi
Version: 0.0.3
Summary: API package for BKK Futár API
Author: MagicNoThief and zselyigy
Author-email: <zselyig@gmail.com>
Keywords: python,api,bkk,futár
Classifier: Development Status :: 1 - Planning
Classifier: Intended Audience :: Developers
Classifier: Programming Language :: Python :: 3
Classifier: Operating System :: Unix
Classifier: Operating System :: MacOS :: MacOS X
Classifier: Operating System :: Microsoft :: Windows
License-File: LICENSE
Requires-Dist: requests
